platos_closet/__init__.py
platos_closet/detection.py
platos_closet-1.1.1.dist-info/LICENSE
platos_closet-1.1.1.dist-info/METADATA
platos_closet-1.1.1.dist-info/WHEEL
platos_closet-1.1.1.dist-info/top_level.txt
platos_closet-1.1.1.dist-info/RECORD
